<annotation>
	<folder>JPEGImages</folder>
	<filename>Apple_109.jpg</filename>
	<path>D:\PycharmProjects\VOC2012\JPEGImages\Apple_109.jpg</path>
	<source>
		<database>Unknown</database>
	</source>
	<size>
		<width>1952</width>
		<height>1865</height>
		<depth>3</depth>
	</size>
	<segmented>0</segmented>
	<object>
		<name>apple</name>
		<pose>Unspecified</pose>
		<truncated>0</truncated>
		<difficult>0</difficult>
		<bndbox>
			<xmin>563</xmin>
			<ymin>582</ymin>
			<xmax>734</xmax>
			<ymax>771</ymax>
		</bndbox>
	</object>
	<object>
		<name>apple</name>
		<pose>Unspecified</pose>
		<truncated>0</truncated>
		<difficult>0</difficult>
		<bndbox>
			<xmin>963</xmin>
			<ymin>576</ymin>
			<xmax>1164</xmax>
			<ymax>789</ymax>
		</bndbox>
	</object>
	<object>
		<name>apple</name>
		<pose>Unspecified</pose>
		<truncated>0</truncated>
		<difficult>0</difficult>
		<bndbox>
			<xmin>919</xmin>
			<ymin>1084</ymin>
			<xmax>1124</xmax>
			<ymax>1277</ymax>
		</bndbox>
	</object>
	<object>
		<name>apple</name>
		<pose>Unspecified</pose>
		<truncated>0</truncated>
		<difficult>0</difficult>
		<bndbox>
			<xmin>1047</xmin>
			<ymin>1210</ymin>
			<xmax>1244</xmax>
			<ymax>1385</ymax>
		</bndbox>
	</object>
</annotation>
