<annotation>
	<folder>JPEGImages</folder>
	<filename>Apple_107.jpg</filename>
	<path>D:\PycharmProjects\VOC2012\JPEGImages\Apple_107.jpg</path>
	<source>
		<database>Unknown</database>
	</source>
	<size>
		<width>1024</width>
		<height>768</height>
		<depth>3</depth>
	</size>
	<segmented>0</segmented>
	<object>
		<name>apple</name>
		<pose>Unspecified</pose>
		<truncated>0</truncated>
		<difficult>0</difficult>
		<bndbox>
			<xmin>254</xmin>
			<ymin>321</ymin>
			<xmax>508</xmax>
			<ymax>598</ymax>
		</bndbox>
	</object>
	<object>
		<name>apple</name>
		<pose>Unspecified</pose>
		<truncated>0</truncated>
		<difficult>0</difficult>
		<bndbox>
			<xmin>492</xmin>
			<ymin>371</ymin>
			<xmax>759</xmax>
			<ymax>651</ymax>
		</bndbox>
	</object>
	<object>
		<name>apple</name>
		<pose>Unspecified</pose>
		<truncated>0</truncated>
		<difficult>0</difficult>
		<bndbox>
			<xmin>401</xmin>
			<ymin>340</ymin>
			<xmax>612</xmax>
			<ymax>636</ymax>
		</bndbox>
	</object>
</annotation>
