<annotation>
	<folder>Orange</folder>
	<filename>Orange_145.jpg</filename>
	<path>D:\PycharmProjects\VOC2012\JPEGImages\Orange\Orange_145.jpg</path>
	<source>
		<database>Unknown</database>
	</source>
	<size>
		<width>450</width>
		<height>300</height>
		<depth>3</depth>
	</size>
	<segmented>0</segmented>
	<object>
		<name>orange</name>
		<pose>Unspecified</pose>
		<truncated>0</truncated>
		<difficult>0</difficult>
		<bndbox>
			<xmin>146</xmin>
			<ymin>122</ymin>
			<xmax>245</xmax>
			<ymax>225</ymax>
		</bndbox>
	</object>
	<object>
		<name>orange</name>
		<pose>Unspecified</pose>
		<truncated>0</truncated>
		<difficult>0</difficult>
		<bndbox>
			<xmin>282</xmin>
			<ymin>91</ymin>
			<xmax>374</xmax>
			<ymax>186</ymax>
		</bndbox>
	</object>
</annotation>
