<annotation>
	<folder>Orange</folder>
	<filename>Orange_319.jpg</filename>
	<path>D:\PycharmProjects\VOC2012\JPEGImages\Orange\Orange_319.jpg</path>
	<source>
		<database>Unknown</database>
	</source>
	<size>
		<width>500</width>
		<height>375</height>
		<depth>3</depth>
	</size>
	<segmented>0</segmented>
	<object>
		<name>orange</name>
		<pose>Unspecified</pose>
		<truncated>0</truncated>
		<difficult>0</difficult>
		<bndbox>
			<xmin>36</xmin>
			<ymin>129</ymin>
			<xmax>189</xmax>
			<ymax>289</ymax>
		</bndbox>
	</object>
	<object>
		<name>orange</name>
		<pose>Unspecified</pose>
		<truncated>0</truncated>
		<difficult>0</difficult>
		<bndbox>
			<xmin>142</xmin>
			<ymin>49</ymin>
			<xmax>321</xmax>
			<ymax>241</ymax>
		</bndbox>
	</object>
	<object>
		<name>orange</name>
		<pose>Unspecified</pose>
		<truncated>0</truncated>
		<difficult>0</difficult>
		<bndbox>
			<xmin>278</xmin>
			<ymin>94</ymin>
			<xmax>473</xmax>
			<ymax>284</ymax>
		</bndbox>
	</object>
</annotation>
